trojan_rabbit/__init__.py
trojan_rabbit/dynamicmethod.py
trojan_rabbit-0.0.1.dist-info/LICENSE
trojan_rabbit-0.0.1.dist-info/METADATA
trojan_rabbit-0.0.1.dist-info/WHEEL
trojan_rabbit-0.0.1.dist-info/top_level.txt
trojan_rabbit-0.0.1.dist-info/RECORD
