Metadata-Version: 2.1
Name: trojan-rabbit
Version: 0.0.1
Summary: Collection of python extras, like decorator @dynamicmethod
Author-email: Janos Gerzson <gerzsonj@gmail.com>
Project-URL: Homepage, https://github.com/grzs/trojan-rabbit
Project-URL: Bug Tracker, https://github.com/grzs/trojan-rabbit/issues
Classifier: Programming Language :: Python :: 3
Classifier: License :: OSI Approved :: MIT License
Classifier: Operating System :: OS Independent
Requires-Python: >=3.0
License-File: LICENSE
